dj_twilio_sms/__init__.py
dj_twilio_sms/admin.py
dj_twilio_sms/decorators.py
dj_twilio_sms/models.py
dj_twilio_sms/serializers.py
dj_twilio_sms/tests.py
dj_twilio_sms/urls.py
dj_twilio_sms/utils.py
dj_twilio_sms/views.py
dj_twilio_sms/migrations/0001_initial.py
dj_twilio_sms/migrations/0002_auto_20170120_0334.py
dj_twilio_sms/migrations/__init__.py
dj_twilio_sms-2.1.0.dist-info/DESCRIPTION.rst
dj_twilio_sms-2.1.0.dist-info/METADATA
dj_twilio_sms-2.1.0.dist-info/RECORD
dj_twilio_sms-2.1.0.dist-info/WHEEL
dj_twilio_sms-2.1.0.dist-info/metadata.json
dj_twilio_sms-2.1.0.dist-info/top_level.txt
