Metadata-Version: 1.1
Name: dj-twilio-sms
Version: 2.1.0
Summary: Twilio SMS Integration for Django
Home-page: https://github.com/mastizada/dj-twilio-sms
Author: Emin Mastizada
Author-email: emin@linux.com
License: MIT
Download-URL: https://github.com/mastizada/dj-twilio-sms/zipball/master
Keywords: django twilio sms
Platform: UNKNOWN
Classifier: Development Status :: 5 - Production/Stable
Classifier: License :: OSI Approved :: MIT License
Classifier: Environment :: Web Environment
Classifier: Framework :: Django
Classifier: Intended Audience :: Developers
Classifier: Operating System :: OS Independent
Classifier: Programming Language :: Python
Classifier: Programming Language :: Python :: 2.7
Classifier: Programming Language :: Python :: 3.5
Classifier: Topic :: Software Development :: Libraries :: Python Modules
